{
  "success": true,
  "total_matches": 43,
  "updated_at": "2026-06-04T13:45:22.945Z",
  "matches": [
    {
      "name": "CYBERSHOKE vs Acend lúc 18:00",
      "link": "https://xoilacztu.tv/truc-tiep/cybershoke-vs-acend-luc-1800-ngay-04-06-2026/",
      "runtime": 1780570800,
      "datetime": "2026-06-04T11:00:00.000Z"
    },
    {
      "name": "Taro Daniel vs Damir Dzumhur lúc 18:20",
      "link": "https://xoilacztu.tv/truc-tiep/taro-daniel-vs-damir-dzumhur-luc-1820-ngay-04-06-2026/",
      "runtime": 1780572000,
      "datetime": "2026-06-04T11:20:00.000Z"
    },
    {
      "name": "Nữ Trung Quốc vs Nữ Thái Lan lúc 18:30",
      "link": "https://xoilacztu.tv/truc-tiep/nu-trung-quoc-vs-nu-thai-lan-luc-1830-ngay-04-06-2026/",
      "runtime": 1780572600,
      "datetime": "2026-06-04T11:30:00.000Z"
    },
    {
      "name": "Campuchia vs Bhutan lúc 19:00 | RIO",
      "link": "https://xoilacztu.tv/truc-tiep/campuchia-vs-bhutan-luc-1900-ngay-04-06-2026/",
      "runtime": 1780574400,
      "datetime": "2026-06-04T12:00:00.000Z"
    },
    {
      "name": "SV Wals-Grunau vs Rheindorf Altach B lúc 19:00",
      "link": "https://xoilacztu.tv/truc-tiep/sv-wals-grunau-vs-rheindorf-altach-b-luc-1900-ngay-04-06-2026/",
      "runtime": 1780574400,
      "datetime": "2026-06-04T12:00:00.000Z"
    },
    {
      "name": "Pasay Voyagers vs Caloocan Kankaloo\t lúc 19:00 | ALAN",
      "link": "https://xoilacztu.tv/truc-tiep/pasay-voyagers-vs-caloocan-kankaloo-luc-1900-ngay-04-06-2026/",
      "runtime": 1780574400,
      "datetime": "2026-06-04T12:00:00.000Z"
    },
    {
      "name": "Robin Montgomery vs Lea Boskovic lúc 19:00",
      "link": "https://xoilacztu.tv/truc-tiep/robin-montgomery-vs-lea-boskovic-luc-1900-ngay-04-06-2026/",
      "runtime": 1780574400,
      "datetime": "2026-06-04T12:00:00.000Z"
    },
    {
      "name": "Glyph vs Execration lúc 19:00",
      "link": "https://xoilacztu.tv/truc-tiep/glyph-vs-execration-luc-1900-ngay-04-06-2026/",
      "runtime": 1780574400,
      "datetime": "2026-06-04T12:00:00.000Z"
    },
    {
      "name": "Celine Naef vs Mary Stoiana lúc 18:10",
      "link": "https://xoilacztu.tv/truc-tiep/celine-naef-vs-mary-stoiana-luc-1810-ngay-04-06-2026/",
      "runtime": 1780574700,
      "datetime": "2026-06-04T12:05:00.000Z"
    },
    {
      "name": "Marco Trungelliti vs Hsu Yu-hsiou lúc 18:10",
      "link": "https://xoilacztu.tv/truc-tiep/marco-trungelliti-vs-hsu-yu-hsiou-luc-1810-ngay-04-06-2026/",
      "runtime": 1780575000,
      "datetime": "2026-06-04T12:10:00.000Z"
    },
    {
      "name": "Max Hans Rehberg vs Marvin Moeller lúc 19:20",
      "link": "https://xoilacztu.tv/truc-tiep/max-hans-rehberg-vs-marvin-moeller-luc-1920-ngay-04-06-2026/",
      "runtime": 1780575600,
      "datetime": "2026-06-04T12:20:00.000Z"
    },
    {
      "name": "Team Falcons vs Team Liquid lúc 19:30",
      "link": "https://xoilacztu.tv/truc-tiep/team-falcons-vs-team-liquid-luc-1930-ngay-04-06-2026/",
      "runtime": 1780575840,
      "datetime": "2026-06-04T12:24:00.000Z"
    },
    {
      "name": "Oktepa vs Gulistan lúc 20:00",
      "link": "https://xoilacztu.tv/truc-tiep/oktepa-vs-gulistan-luc-2000-ngay-04-06-2026/",
      "runtime": 1780576200,
      "datetime": "2026-06-04T12:30:00.000Z"
    },
    {
      "name": "FC Kattaqo  vs FarDU lúc 19:30",
      "link": "https://xoilacztu.tv/truc-tiep/fc-kattaqo-vs-fardu-luc-2000-ngay-04-06-2026/",
      "runtime": 1780576200,
      "datetime": "2026-06-04T12:30:00.000Z"
    },
    {
      "name": "Cần Thơ Catfish vs Hà Nội Buffalo lúc 19:30 | TOMMY",
      "link": "https://xoilacztu.tv/truc-tiep/can-tho-catfish-vs-ha-noi-buffalo-luc-1930-ngay-04-06-2026/",
      "runtime": 1780576200,
      "datetime": "2026-06-04T12:30:00.000Z"
    },
    {
      "name": "Hynek Barton vs Norbert Gombos lúc 19:30",
      "link": "https://xoilacztu.tv/truc-tiep/hynek-barton-vs-norbert-gombos-luc-1930-ngay-04-06-2026/",
      "runtime": 1780576200,
      "datetime": "2026-06-04T12:30:00.000Z"
    },
    {
      "name": "FC Kitzbuhel vs St. Johann lúc 19:30",
      "link": "https://xoilacztu.tv/truc-tiep/fc-kitzbuhel-vs-st-johann-luc-1930-ngay-04-06-2026/",
      "runtime": 1780576800,
      "datetime": "2026-06-04T12:40:00.000Z"
    },
    {
      "name": "Nozomi Okuhara vs Tomoka Miyazaki lúc 20:00",
      "link": "https://xoilacztu.tv/truc-tiep/nozomi-okuhara-vs-tomoka-miyazaki-luc-2000-ngay-04-06-2026/",
      "runtime": 1780577100,
      "datetime": "2026-06-04T12:45:00.000Z"
    },
    {
      "name": "Alexandra Eala vs Alina Charaeva lúc 17:40",
      "link": "https://xoilacztu.tv/truc-tiep/alexandra-eala-vs-alina-charaeva-luc-1740-ngay-04-06-2026/",
      "runtime": 1780577400,
      "datetime": "2026-06-04T12:50:00.000Z"
    },
    {
      "name": "Timor Leste U19 vs Indonesia U19 lúc 20:00 | MAX",
      "link": "https://xoilacztu.tv/truc-tiep/timor-leste-u19-vs-indonesia-u19-luc-2000-ngay-04-06-2026/",
      "runtime": 1780578000,
      "datetime": "2026-06-04T13:00:00.000Z"
    },
    {
      "name": "Shurtan Guzor  vs Metallurg Bekobod lúc 20:00",
      "link": "https://xoilacztu.tv/truc-tiep/shurtan-guzor-vs-metallurg-bekobod-luc-2000-ngay-04-06-2026/",
      "runtime": 1780578000,
      "datetime": "2026-06-04T13:00:00.000Z"
    },
    {
      "name": "Lesotho vs Kenya lúc 20:00",
      "link": "https://xoilacztu.tv/truc-tiep/lesotho-vs-kenya-luc-2000-ngay-04-06-2026/",
      "runtime": 1780578000,
      "datetime": "2026-06-04T13:00:00.000Z"
    },
    {
      "name": "Respublika FA vs Qiziriq FC lúc 20:00",
      "link": "https://xoilacztu.tv/truc-tiep/respublika-fa-vs-qiziriq-fc-luc-2000-ngay-04-06-2026/",
      "runtime": 1780578000,
      "datetime": "2026-06-04T13:00:00.000Z"
    },
    {
      "name": "Marta Kostyuk vs Mirra Andreeva lúc 20:00 | VIC",
      "link": "https://xoilacztu.tv/truc-tiep/marta-kostyuk-vs-mirra-andreeva-luc-2000-ngay-04-06-2026/",
      "runtime": 1780578000,
      "datetime": "2026-06-04T13:00:00.000Z"
    },
    {
      "name": "Elina Avanesyan vs Dominika Salkova lúc 20:10",
      "link": "https://xoilacztu.tv/truc-tiep/elina-avanesyan-vs-dominika-salkova-luc-2010-ngay-04-06-2026/",
      "runtime": 1780578600,
      "datetime": "2026-06-04T13:10:00.000Z"
    },
    {
      "name": "Mayar Sherif vs Georgia Pedone lúc 20:20",
      "link": "https://xoilacztu.tv/truc-tiep/mayar-sherif-vs-georgia-pedone-luc-2020-ngay-04-06-2026/",
      "runtime": 1780579200,
      "datetime": "2026-06-04T13:20:00.000Z"
    },
    {
      "name": "Henrique Rocha vs Dusan Lajovic lúc 20:10",
      "link": "https://xoilacztu.tv/truc-tiep/henrique-rocha-vs-dusan-lajovic-luc-2010-ngay-04-06-2026/",
      "runtime": 1780579200,
      "datetime": "2026-06-04T13:20:00.000Z"
    },
    {
      "name": "Katie Swan vs Taylah Preston lúc 20:40",
      "link": "https://xoilacztu.tv/truc-tiep/katie-swan-vs-taylah-preston-luc-2040-ngay-04-06-2026/",
      "runtime": 1780580400,
      "datetime": "2026-06-04T13:40:00.000Z"
    },
    {
      "name": "Ong Xin Yee/Carmen Ting vs Rui Hirokami/Sayaka Hobara lúc 18:10",
      "link": "https://xoilacztu.tv/truc-tiep/ong-xin-yee-carmen-ting-vs-rui-hirokami-sayaka-hobara-luc-1810-ngay-04-06-2026/",
      "runtime": 1780580700,
      "datetime": "2026-06-04T13:45:00.000Z"
    },
    {
      "name": "Sim Yu-Jin vs Wang Zhiyi lúc 19:00",
      "link": "https://xoilacztu.tv/truc-tiep/sim-yu-jin-vs-wang-zhiyi-luc-1900-ngay-04-06-2026/",
      "runtime": 1780581000,
      "datetime": "2026-06-04T13:50:00.000Z"
    },
    {
      "name": "PWD de Bamenda vs Canon Yaounde lúc 21:00",
      "link": "https://xoilacztu.tv/truc-tiep/pwd-de-bamenda-vs-canon-yaounde-luc-2100-ngay-03-06-2026/",
      "runtime": 1780581600,
      "datetime": "2026-06-04T14:00:00.000Z"
    },
    {
      "name": "Rithvik Choudary Bollipalli/Ramkumar Ramanathan vs Andrew Fenty/Brandon Perez lúc 21:00",
      "link": "https://xoilacztu.tv/truc-tiep/rithvik-choudary-bollipalli-ramkumar-ramanathan-vs-andrew-fenty-brandon-perez-luc-2100-ngay-04-06-2026/",
      "runtime": 1780581600,
      "datetime": "2026-06-04T14:00:00.000Z"
    },
    {
      "name": "Valentin Basel/Bruno Oliveira vs Nicolas Mejia/Adria Soriano Barrera lúc 21:00",
      "link": "https://xoilacztu.tv/truc-tiep/valentin-basel-bruno-oliveira-vs-nicolas-mejia-adria-soriano-barrera-luc-0400-ngay-03-06-2026/",
      "runtime": 1780581600,
      "datetime": "2026-06-04T14:00:00.000Z"
    },
    {
      "name": "brazylijski luz vs The Last Resort lúc 21:00",
      "link": "https://xoilacztu.tv/truc-tiep/brazylijski-luz-vs-the-last-resort-luc-2100-ngay-04-06-2026/",
      "runtime": 1780581600,
      "datetime": "2026-06-04T14:00:00.000Z"
    },
    {
      "name": "100 Thieves vs Ursa lúc 21:00",
      "link": "https://xoilacztu.tv/truc-tiep/100-thieves-vs-ursa-luc-2100-ngay-04-06-2026/",
      "runtime": 1780581600,
      "datetime": "2026-06-04T14:00:00.000Z"
    },
    {
      "name": "Diana Shnaider vs Maja Chwalinska lúc 21:10 | LUCAS",
      "link": "https://xoilacztu.tv/truc-tiep/diana-shnaider-vs-maja-chwalinska-luc-2110-ngay-04-06-2026/",
      "runtime": 1780582200,
      "datetime": "2026-06-04T14:10:00.000Z"
    },
    {
      "name": "Shi Yuqi vs Yushi Tanaka lúc 19:00",
      "link": "https://xoilacztu.tv/truc-tiep/shi-yuqi-vs-yushi-tanaka-luc-1900-ngay-04-06-2026/",
      "runtime": 1780584000,
      "datetime": "2026-06-04T14:40:00.000Z"
    },
    {
      "name": "Nữ Mauritius vs Nữ Djibouti lúc 22:00 | JOHAN",
      "link": "https://xoilacztu.tv/truc-tiep/nu-mauritius-vs-nu-djibouti-luc-2200-ngay-04-06-2026/",
      "runtime": 1780585200,
      "datetime": "2026-06-04T15:00:00.000Z"
    },
    {
      "name": "Al-Ahli tripoli vs Al Akhdar lúc 22:00",
      "link": "https://xoilacztu.tv/truc-tiep/al-ahli-tripoli-vs-al-akhdar-luc-2200-ngay-04-06-2026/",
      "runtime": 1780585200,
      "datetime": "2026-06-04T15:00:00.000Z"
    },
    {
      "name": "Hayato Matsuoka vs Henry Searle lúc 22:00",
      "link": "https://xoilacztu.tv/truc-tiep/hayato-matsuoka-vs-henry-searle-luc-2200-ngay-04-06-2026/",
      "runtime": 1780585200,
      "datetime": "2026-06-04T15:00:00.000Z"
    },
    {
      "name": "Murphy Cassone vs Yuta Shimizu lúc 22:00",
      "link": "https://xoilacztu.tv/truc-tiep/murphy-cassone-vs-yuta-shimizu-luc-2200-ngay-04-06-2026/",
      "runtime": 1780585200,
      "datetime": "2026-06-04T15:00:00.000Z"
    },
    {
      "name": "Movistar KOI Fénix vs UCAM Esports Club lúc 22:00",
      "link": "https://xoilacztu.tv/truc-tiep/movistar-koi-fenix-vs-ucam-esports-club-luc-2200-ngay-04-06-2026/",
      "runtime": 1780585200,
      "datetime": "2026-06-04T15:00:00.000Z"
    },
    {
      "name": "AIFK Turku vs P-Iirot lúc 22:30 | SILVA",
      "link": "https://xoilacztu.tv/truc-tiep/aifk-turku-vs-p-iirot-luc-2230-ngay-04-06-2026/",
      "runtime": 1780587000,
      "datetime": "2026-06-04T15:30:00.000Z"
    }
  ]
}