{
  "success": true,
  "total_matches": 52,
  "updated_at": "2026-05-24T23:16:50.558Z",
  "matches": [
    {
      "name": "Goh Sze Fei/Nur Izzuddin Rumsani vs Daniel Lundgaard/Mads Vestergaard lúc 14:20",
      "link": "/truc-tiep/goh-sze-fei-nur-izzuddin-rumsani-vs-daniel-lundgaard-mads-vestergaard-luc-1420-ngay-24-05-2026/",
      "runtime": 1779612300,
      "datetime": "2026-05-24T08:45:00.000Z"
    },
    {
      "name": "Nữ Italy vs Nữ Ba Lan lúc 02:00",
      "link": "/truc-tiep/nu-italy-vs-nu-ba-lan-luc-0200-ngay-25-05-2026/",
      "runtime": 1779649200,
      "datetime": "2026-05-24T19:00:00.000Z"
    },
    {
      "name": "LYON vs Team Liquid lúc 03:00",
      "link": "/truc-tiep/lyon-vs-team-liquid-luc-0300-ngay-25-05-2026/",
      "runtime": 1779652800,
      "datetime": "2026-05-24T20:00:00.000Z"
    },
    {
      "name": "Estudiantes Merida vs Metropolitanos FC lúc 04:00",
      "link": "/truc-tiep/estudiantes-merida-vs-metropolitanos-fc-luc-0400-ngay-25-05-2026/",
      "runtime": 1779656400,
      "datetime": "2026-05-24T21:00:00.000Z"
    },
    {
      "name": "JC Roddick vs Christian Langmo lúc 01:30",
      "link": "/truc-tiep/jc-roddick-vs-christian-langmo-luc-0130-ngay-25-05-2026/",
      "runtime": 1779657000,
      "datetime": "2026-05-24T21:10:00.000Z"
    },
    {
      "name": "Corinthians SP vs Atlético Mineiro lúc 04:30 | HELLO",
      "link": "/truc-tiep/corinthians-sp-vs-atletico-mineiro-luc-0430-ngay-25-05-2026/",
      "runtime": 1779658200,
      "datetime": "2026-05-24T21:30:00.000Z"
    },
    {
      "name": "Defensor SC vs CA Penarol lúc 04:30",
      "link": "/truc-tiep/defensor-sc-vs-ca-penarol-luc-0430-ngay-25-05-2026/",
      "runtime": 1779658200,
      "datetime": "2026-05-24T21:30:00.000Z"
    },
    {
      "name": "America MG vs Vila Nova lúc 04:30",
      "link": "/truc-tiep/america-mg-vs-vila-nova-luc-0430-ngay-25-05-2026/",
      "runtime": 1779658200,
      "datetime": "2026-05-24T21:30:00.000Z"
    },
    {
      "name": "Gimnasia yTiro vs Gimnasia Jujuy lúc 04:30",
      "link": "/truc-tiep/gimnasia-ytiro-vs-gimnasia-jujuy-luc-0430-ngay-25-05-2026/",
      "runtime": 1779658200,
      "datetime": "2026-05-24T21:30:00.000Z"
    },
    {
      "name": "Club Atletico Guemes vs Patronato Parana lúc 04:30",
      "link": "/truc-tiep/club-atletico-guemes-vs-patronato-parana-luc-0430-ngay-25-05-2026/",
      "runtime": 1779658200,
      "datetime": "2026-05-24T21:30:00.000Z"
    },
    {
      "name": "Nữ Club Rubio Nu vs Nữ 2 de Mayo  lúc 04:30",
      "link": "/truc-tiep/nu-club-rubio-nu-vs-nu-2-de-mayo-luc-0430-ngay-25-05-2026/",
      "runtime": 1779658200,
      "datetime": "2026-05-24T21:30:00.000Z"
    },
    {
      "name": "Nữ Junior vs Nữ Fortaleza lúc 04:30",
      "link": "/truc-tiep/nu-junior-vs-nu-fortaleza-luc-0430-ngay-25-05-2026/",
      "runtime": 1779658200,
      "datetime": "2026-05-24T21:30:00.000Z"
    },
    {
      "name": "Marineros de Puerto Plata vs Titanes del Licey lúc 04:30",
      "link": "/truc-tiep/marineros-de-puerto-plata-vs-titanes-del-licey-luc-0430-ngay-25-05-2026/",
      "runtime": 1779658200,
      "datetime": "2026-05-24T21:30:00.000Z"
    },
    {
      "name": "Guaiqueries vs Trotamundos lúc 04:30",
      "link": "/truc-tiep/guaiqueries-vs-trotamundos-luc-0430-ngay-25-05-2026/",
      "runtime": 1779658200,
      "datetime": "2026-05-24T21:30:00.000Z"
    },
    {
      "name": "Avaí FC vs Goiás EC lúc 05:00",
      "link": "/truc-tiep/avai-fc-vs-goias-ec-luc-0500-ngay-25-05-2026/",
      "runtime": 1779660000,
      "datetime": "2026-05-24T22:00:00.000Z"
    },
    {
      "name": "Univ Catolica vs Colo Colo lúc 05:00",
      "link": "/truc-tiep/univ-catolica-vs-colo-colo-luc-0500-ngay-25-05-2026/",
      "runtime": 1779660000,
      "datetime": "2026-05-24T22:00:00.000Z"
    },
    {
      "name": "San Martin Tucuman vs Atletico Atlanta lúc 05:00",
      "link": "/truc-tiep/san-martin-tucuman-vs-atletico-atlanta-luc-0500-ngay-25-05-2026/",
      "runtime": 1779660000,
      "datetime": "2026-05-24T22:00:00.000Z"
    },
    {
      "name": "Staten Island ASC vs FC Motown B lúc 05:00",
      "link": "/truc-tiep/staten-island-asc-vs-fc-motown-b-luc-0500-ngay-25-05-2026/",
      "runtime": 1779660000,
      "datetime": "2026-05-24T22:00:00.000Z"
    },
    {
      "name": "Volta Redonda vs Ypiranga RS lúc 05:00",
      "link": "/truc-tiep/volta-redonda-vs-ypiranga-rs-luc-0500-ngay-25-05-2026/",
      "runtime": 1779660000,
      "datetime": "2026-05-24T22:00:00.000Z"
    },
    {
      "name": "SV Estrella vs SV River Plate lúc 05:00",
      "link": "/truc-tiep/sv-estrella-vs-sv-river-plate-luc-0500-ngay-25-05-2026/",
      "runtime": 1779660000,
      "datetime": "2026-05-24T22:00:00.000Z"
    },
    {
      "name": "Montego Bay Utd vs Mount Pleasant FA lúc 05:00",
      "link": "/truc-tiep/montego-bay-utd-vs-mount-pleasant-fa-luc-0500-ngay-25-05-2026/",
      "runtime": 1779660000,
      "datetime": "2026-05-24T22:00:00.000Z"
    },
    {
      "name": "Nữ Seattle Storm vs Nữ Mystics lúc 05:00 | STEP",
      "link": "/truc-tiep/nu-seattle-storm-vs-nu-mystics-luc-0500-ngay-25-05-2026/",
      "runtime": 1779660000,
      "datetime": "2026-05-24T22:00:00.000Z"
    },
    {
      "name": "Edmonton Stingers vs Niagara River Lions lúc 05:00",
      "link": "/truc-tiep/edmonton-stingers-vs-niagara-river-lions-luc-0500-ngay-25-05-2026/",
      "runtime": 1779660000,
      "datetime": "2026-05-24T22:00:00.000Z"
    },
    {
      "name": "Leon Nicaragua vs Jaguares UAM lúc 05:00",
      "link": "/truc-tiep/leon-nicaragua-vs-jaguares-uam-luc-0500-ngay-25-05-2026/",
      "runtime": 1779660000,
      "datetime": "2026-05-24T22:00:00.000Z"
    },
    {
      "name": "Team Gunnar vs Team King Potato lúc 05:00",
      "link": "/truc-tiep/team-gunnar-vs-team-king-potato-luc-0500-ngay-25-05-2026/",
      "runtime": 1779660780,
      "datetime": "2026-05-24T22:13:00.000Z"
    },
    {
      "name": "Paraguari AC vs Benjamin Aceval lúc 05:30",
      "link": "/truc-tiep/paraguari-ac-vs-benjamin-aceval-luc-0530-ngay-25-05-2026/",
      "runtime": 1779661800,
      "datetime": "2026-05-24T22:30:00.000Z"
    },
    {
      "name": "Point Michel FC vs Mahaut Soca Strikers lúc 05:30",
      "link": "/truc-tiep/point-michel-fc-vs-mahaut-soca-strikers-luc-0530-ngay-25-05-2026/",
      "runtime": 1779661800,
      "datetime": "2026-05-24T22:30:00.000Z"
    },
    {
      "name": "Inter Miami vs Philadelphia Union lúc 06:00 | FINN",
      "link": "/truc-tiep/inter-miami-vs-philadelphia-union-luc-0600-ngay-25-05-2026/",
      "runtime": 1779663600,
      "datetime": "2026-05-24T23:00:00.000Z"
    },
    {
      "name": "Vancouver Whitecaps II vs Real Monarchs lúc 06:00",
      "link": "/truc-tiep/vancouver-whitecaps-ii-vs-real-monarchs-luc-0600-ngay-25-05-2026/",
      "runtime": 1779663600,
      "datetime": "2026-05-24T23:00:00.000Z"
    },
    {
      "name": "NY Red Bulls B vs Connecticut United FC lúc 06:00",
      "link": "/truc-tiep/ny-red-bulls-b-vs-connecticut-united-fc-luc-0600-ngay-25-05-2026/",
      "runtime": 1779663600,
      "datetime": "2026-05-24T23:00:00.000Z"
    },
    {
      "name": "Orlando City B vs Inter Miami B lúc 06:00",
      "link": "/truc-tiep/orlando-city-b-vs-inter-miami-b-luc-0600-ngay-25-05-2026/",
      "runtime": 1779663600,
      "datetime": "2026-05-24T23:00:00.000Z"
    },
    {
      "name": "Spokane Velocity vs Sarasota Paradise lúc 06:00",
      "link": "/truc-tiep/spokane-velocity-vs-sarasota-paradise-luc-0600-ngay-25-05-2026/",
      "runtime": 1779663600,
      "datetime": "2026-05-24T23:00:00.000Z"
    },
    {
      "name": "CD Motagua vs Marathon lúc 06:00",
      "link": "/truc-tiep/cd-motagua-vs-marathon-luc-0600-ngay-25-05-2026/",
      "runtime": 1779663600,
      "datetime": "2026-05-24T23:00:00.000Z"
    },
    {
      "name": "Delfin SC vs Barcelona SC lúc 06:10 | YUNO",
      "link": "/truc-tiep/delfin-sc-vs-barcelona-sc-luc-0610-ngay-25-05-2026/",
      "runtime": 1779664200,
      "datetime": "2026-05-24T23:10:00.000Z"
    },
    {
      "name": "Vasco da Gama vs RB Bragantino lúc 06:30 | ZARA",
      "link": "/truc-tiep/vasco-da-gama-vs-rb-bragantino-luc-0630-ngay-25-05-2026/",
      "runtime": 1779665400,
      "datetime": "2026-05-24T23:30:00.000Z"
    },
    {
      "name": "Aurora vs Oriente Petrolero lúc 06:30",
      "link": "/truc-tiep/aurora-vs-oriente-petrolero-luc-0630-ngay-25-05-2026/",
      "runtime": 1779665400,
      "datetime": "2026-05-24T23:30:00.000Z"
    },
    {
      "name": "Operario PR vs Criciuma lúc 06:30",
      "link": "/truc-tiep/operario-pr-vs-criciuma-luc-0630-ngay-25-05-2026/",
      "runtime": 1779665400,
      "datetime": "2026-05-24T23:30:00.000Z"
    },
    {
      "name": "Nữ Northern Virginia vs Nữ Loudoun United FC lúc 06:30",
      "link": "/truc-tiep/nu-northern-virginia-vs-nu-loudoun-united-fc-luc-0630-ngay-25-05-2026/",
      "runtime": 1779665400,
      "datetime": "2026-05-24T23:30:00.000Z"
    },
    {
      "name": "Teniente Benjamin Matienzo vs El Ceibo lúc 06:30",
      "link": "/truc-tiep/teniente-benjamin-matienzo-vs-el-ceibo-luc-0630-ngay-25-05-2026/",
      "runtime": 1779665400,
      "datetime": "2026-05-24T23:30:00.000Z"
    },
    {
      "name": "Columbus Crew B vs Toronto FC II lúc 07:00",
      "link": "/truc-tiep/columbus-crew-b-vs-toronto-fc-ii-luc-0700-ngay-25-05-2026/",
      "runtime": 1779667200,
      "datetime": "2026-05-25T00:00:00.000Z"
    },
    {
      "name": "San Luis Quillota vs CD Magallanes lúc 07:00",
      "link": "/truc-tiep/san-luis-quillota-vs-cd-magallanes-luc-0700-ngay-25-05-2026/",
      "runtime": 1779667200,
      "datetime": "2026-05-25T00:00:00.000Z"
    },
    {
      "name": "SV Caiquetio vs SV Brazil Juniors lúc 07:00",
      "link": "/truc-tiep/sv-caiquetio-vs-sv-brazil-juniors-luc-0700-ngay-25-05-2026/",
      "runtime": 1779667200,
      "datetime": "2026-05-25T00:00:00.000Z"
    },
    {
      "name": "Gigantes Carolina vs Nữ Leones de Ponce lúc 07:00",
      "link": "/truc-tiep/gigantes-carolina-vs-nu-leones-de-ponce-luc-0700-ngay-25-05-2026/",
      "runtime": 1779667200,
      "datetime": "2026-05-25T00:00:00.000Z"
    },
    {
      "name": "Vancouver Bandits vs Calgary Surge lúc 07:00",
      "link": "/truc-tiep/vancouver-bandits-vs-calgary-surge-luc-0700-ngay-25-05-2026/",
      "runtime": 1779667200,
      "datetime": "2026-05-25T00:00:00.000Z"
    },
    {
      "name": "San Antonio Spurs vs Oklahoma City Thunder lúc 07:00 | TOMMY",
      "link": "/truc-tiep/san-antonio-spurs-vs-oklahoma-city-thunder-luc-0700-ngay-25-05-2026/",
      "runtime": 1779667200,
      "datetime": "2026-05-25T00:00:00.000Z"
    },
    {
      "name": "Team Monkeys Forever vs Team Dnm lúc 07:00",
      "link": "/truc-tiep/team-monkeys-forever-vs-team-dnm-luc-0700-ngay-25-05-2026/",
      "runtime": 1779667200,
      "datetime": "2026-05-25T00:00:00.000Z"
    },
    {
      "name": "Galorys vs Lp lúc 07:00",
      "link": "/truc-tiep/galorys-vs-lp-luc-0700-ngay-25-05-2026/",
      "runtime": 1779667200,
      "datetime": "2026-05-25T00:00:00.000Z"
    },
    {
      "name": "Pumas U.N.A.M. vs Cruz Azul lúc 08:00 | JAY",
      "link": "/truc-tiep/pumas-u-n-a-m-vs-cruz-azul-luc-0800-ngay-25-05-2026/",
      "runtime": 1779670800,
      "datetime": "2026-05-25T01:00:00.000Z"
    },
    {
      "name": "Colorado ISA vs Utah United lúc 08:00",
      "link": "/truc-tiep/colorado-isa-vs-utah-united-luc-0800-ngay-25-05-2026/",
      "runtime": 1779670800,
      "datetime": "2026-05-25T01:00:00.000Z"
    },
    {
      "name": "Cavalier FC vs Portmore United lúc 08:00",
      "link": "/truc-tiep/cavalier-fc-vs-portmore-united-luc-0800-ngay-25-05-2026/",
      "runtime": 1779670800,
      "datetime": "2026-05-25T01:00:00.000Z"
    },
    {
      "name": "AF Chilibre vs Deportivo Ana Luisa Flores lúc 08:00",
      "link": "/truc-tiep/af-chilibre-vs-deportivo-ana-luisa-flores-luc-0800-ngay-25-05-2026/",
      "runtime": 1779670800,
      "datetime": "2026-05-25T01:00:00.000Z"
    },
    {
      "name": "Los Angeles FC vs Seattle Sounders lúc 08:15 | POLO",
      "link": "/truc-tiep/los-angeles-fc-vs-seattle-sounders-luc-0815-ngay-25-05-2026/",
      "runtime": 1779671700,
      "datetime": "2026-05-25T01:15:00.000Z"
    }
  ]
}