{
  "success": true,
  "total_matches": 51,
  "updated_at": "2026-04-04T04:12:11.804Z",
  "matches": [
    {
      "name": "Guevara Corona D G / Tamayo Mata H B vs Thomas Wiesler/Jana Weissenbach lúc 16:00",
      "link": "/truc-tiep/guevara-corona-d-g-tamayo-mata-h-b-vs-thomas-wiesler-jana-weissenbach-luc-1600-ngay-01-04-2026/",
      "runtime": 1775034000,
      "datetime": "2026-04-01T09:00:00.000Z"
    },
    {
      "name": "Andersen S M / Fliglová N vs Schausberger M / Thurnherr A lúc 16:30",
      "link": "/truc-tiep/andersen-s-m-fliglova-n-vs-schausberger-m-thurnherr-a-luc-1630-ngay-01-04-2026/",
      "runtime": 1775035800,
      "datetime": "2026-04-01T09:30:00.000Z"
    },
    {
      "name": "Facundo Mena/Rodrigo Pacheco Mendez vs Mateus Alves/Matias Soto lúc 07:10",
      "link": "/truc-tiep/facundo-mena-rodrigo-pacheco-mendez-vs-mateus-alves-matias-soto-luc-0710-ngay-04-04-2026/",
      "runtime": 1775261400,
      "datetime": "2026-04-04T00:10:00.000Z"
    },
    {
      "name": "James Duckworth vs Beibit Zhukayev lúc 08:40",
      "link": "/truc-tiep/james-duckworth-vs-beibit-zhukayev-luc-0840-ngay-04-04-2026/",
      "runtime": 1775266800,
      "datetime": "2026-04-04T01:40:00.000Z"
    },
    {
      "name": "Sacramento Kings vs New Orleans Pelicans lúc 09:00 | NEZHA",
      "link": "/truc-tiep/sacramento-kings-vs-new-orleans-pelicans-luc-0900-ngay-04-04-2026/",
      "runtime": 1775268000,
      "datetime": "2026-04-04T02:00:00.000Z"
    },
    {
      "name": "Stockton Kings vs Rip City Remix lúc 09:00",
      "link": "/truc-tiep/stockton-kings-vs-rip-city-remix-luc-0900-ngay-04-04-2026/",
      "runtime": 1775268000,
      "datetime": "2026-04-04T02:00:00.000Z"
    },
    {
      "name": "South Bay Lakers vs Rio Grande Vipers lúc 09:00",
      "link": "/truc-tiep/south-bay-lakers-vs-rio-grande-vipers-luc-0900-ngay-04-04-2026/",
      "runtime": 1775268000,
      "datetime": "2026-04-04T02:00:00.000Z"
    },
    {
      "name": "Nam Ji-sung/Patrik Niklas-Salminen vs Yuta Shimizu/James Kent Trotter lúc 09:00",
      "link": "/truc-tiep/nam-ji-sung-patrik-niklas-salminen-vs-yuta-shimizu-james-kent-trotter-luc-0900-ngay-04-04-2026/",
      "runtime": 1775268000,
      "datetime": "2026-04-04T02:00:00.000Z"
    },
    {
      "name": "Island Bay United vs Miramar Rangers lúc 09:45",
      "link": "/truc-tiep/island-bay-united-vs-miramar-rangers-luc-0945-ngay-04-04-2026/",
      "runtime": 1775270700,
      "datetime": "2026-04-04T02:45:00.000Z"
    },
    {
      "name": "Necaxa vs Mazatlan FC lúc 10:00 | FINN",
      "link": "/truc-tiep/necaxa-vs-mazatlan-fc-luc-1000-ngay-04-04-2026/",
      "runtime": 1775271600,
      "datetime": "2026-04-04T03:00:00.000Z"
    },
    {
      "name": "SKA Khabarovsk-2 vs FC Avangard Kursk lúc 10:00",
      "link": "/truc-tiep/ska-khabarovsk-2-vs-fc-avangard-kursk-luc-1000-ngay-04-04-2026/",
      "runtime": 1775271600,
      "datetime": "2026-04-04T03:00:00.000Z"
    },
    {
      "name": "Whittlesea United vs Dandenong City SC lúc 10:00",
      "link": "/truc-tiep/whittlesea-united-vs-dandenong-city-sc-luc-1000-ngay-04-04-2026/",
      "runtime": 1775271600,
      "datetime": "2026-04-04T03:00:00.000Z"
    },
    {
      "name": "Nữ Football West vs Nữ Perth RedStar lúc 10:00",
      "link": "/truc-tiep/nu-football-west-vs-nu-perth-redstar-luc-1000-ngay-04-04-2026/",
      "runtime": 1775271600,
      "datetime": "2026-04-04T03:00:00.000Z"
    },
    {
      "name": "The Huns vs TYLOO lúc 10:00",
      "link": "/truc-tiep/the-huns-vs-tyloo-luc-1000-ngay-04-04-2026/",
      "runtime": 1775271600,
      "datetime": "2026-04-04T03:00:00.000Z"
    },
    {
      "name": "Ivory vs Carstensz Esports lúc 10:00",
      "link": "/truc-tiep/ivory-vs-carstensz-esports-luc-1000-ngay-04-04-2026/",
      "runtime": 1775271600,
      "datetime": "2026-04-04T03:00:00.000Z"
    },
    {
      "name": "JTEKT vs FC Tokyo lúc 10:05",
      "link": "/truc-tiep/jtekt-vs-fc-tokyo-luc-1005-ngay-04-04-2026/",
      "runtime": 1775271900,
      "datetime": "2026-04-04T03:05:00.000Z"
    },
    {
      "name": "Club Tijuana vs Tigres UANL lúc 10:06 | KEN",
      "link": "/truc-tiep/club-tijuana-vs-tigres-uanl-luc-1006-ngay-04-04-2026/",
      "runtime": 1775271960,
      "datetime": "2026-04-04T03:06:00.000Z"
    },
    {
      "name": "Nữ Central Mariners  vs Nữ Sydney FC lúc 10:15 | JAY",
      "link": "/truc-tiep/nu-central-mariners-vs-nu-sydney-fc-luc-1015-ngay-04-04-2026/",
      "runtime": 1775272500,
      "datetime": "2026-04-04T03:15:00.000Z"
    },
    {
      "name": "Nữ Bulls Academy vs Nữ Sydney Olympic lúc 10:40",
      "link": "/truc-tiep/nu-bulls-academy-vs-nu-sydney-olympic-luc-1040-ngay-04-04-2026/",
      "runtime": 1775274000,
      "datetime": "2026-04-04T03:40:00.000Z"
    },
    {
      "name": "JEF United vs Tokyo Verdy lúc 11:00 | RYAN",
      "link": "/truc-tiep/jef-united-vs-tokyo-verdy-luc-1100-ngay-04-04-2026/",
      "runtime": 1775275200,
      "datetime": "2026-04-04T04:00:00.000Z"
    },
    {
      "name": "Nữ Canberra United vs Nữ Brisbane Roar  lúc 11:00 | HELLO",
      "link": "/truc-tiep/nu-canberra-united-vs-nu-brisbane-roar-luc-1100-ngay-04-04-2026/",
      "runtime": 1775275200,
      "datetime": "2026-04-04T04:00:00.000Z"
    },
    {
      "name": "Liam Broady vs Blake Ellis lúc 11:00",
      "link": "/truc-tiep/liam-broady-vs-blake-ellis-luc-1100-ngay-04-04-2026/",
      "runtime": 1775275200,
      "datetime": "2026-04-04T04:00:00.000Z"
    },
    {
      "name": "Nữ Denso Airybees vs Nữ Hitachi  lúc 11:05",
      "link": "/truc-tiep/nu-denso-airybees-vs-nu-hitachi-luc-1105-ngay-04-04-2026/",
      "runtime": 1775275500,
      "datetime": "2026-04-04T04:05:00.000Z"
    },
    {
      "name": "Voreas Hokkaido vs Panasonic Panthers lúc 11:05",
      "link": "/truc-tiep/voreas-hokkaido-vs-panasonic-panthers-luc-1105-ngay-04-04-2026/",
      "runtime": 1775275500,
      "datetime": "2026-04-04T04:05:00.000Z"
    },
    {
      "name": "Mito Hollyhock vs Kashima Antlers lúc 12:00 | POLO",
      "link": "/truc-tiep/mito-hollyhock-vs-kashima-antlers-luc-1200-ngay-04-04-2026/",
      "runtime": 1775278800,
      "datetime": "2026-04-04T05:00:00.000Z"
    },
    {
      "name": "Jeonbuk Hyundai vs Ulsan Hyundai lúc 12:00 | ASTRA",
      "link": "/truc-tiep/jeonbuk-hyundai-vs-ulsan-hyundai-luc-1200-ngay-04-04-2026/",
      "runtime": 1775278800,
      "datetime": "2026-04-04T05:00:00.000Z"
    },
    {
      "name": "Jeju SK FC vs Bucheon 1995 lúc 12:00 | YUNO",
      "link": "/truc-tiep/jeju-sk-fc-vs-bucheon-1995-luc-1200-ngay-04-04-2026/",
      "runtime": 1775278800,
      "datetime": "2026-04-04T05:00:00.000Z"
    },
    {
      "name": "Tochigi City vs SC Sagamihara lúc 12:00",
      "link": "/truc-tiep/tochigi-city-vs-sc-sagamihara-luc-1200-ngay-04-04-2026/",
      "runtime": 1775278800,
      "datetime": "2026-04-04T05:00:00.000Z"
    },
    {
      "name": "RB Omiya Ardija vs FC Gifu lúc 12:00",
      "link": "/truc-tiep/rb-omiya-ardija-vs-fc-gifu-luc-1200-ngay-04-04-2026/",
      "runtime": 1775278800,
      "datetime": "2026-04-04T05:00:00.000Z"
    },
    {
      "name": "Fujieda MYFC vs  Nagano Parceiro lúc 12:00",
      "link": "/truc-tiep/fujieda-myfc-vs-nagano-parceiro-luc-1200-ngay-04-04-2026/",
      "runtime": 1775278800,
      "datetime": "2026-04-04T05:00:00.000Z"
    },
    {
      "name": "Consadole Sapporo vs Fukushima FC lúc 12:00",
      "link": "/truc-tiep/consadole-sapporo-vs-fukushima-fc-luc-1200-ngay-04-04-2026/",
      "runtime": 1775278800,
      "datetime": "2026-04-04T05:00:00.000Z"
    },
    {
      "name": "Vegalta Sendai vs Thespa Gunma lúc 12:00",
      "link": "/truc-tiep/vegalta-sendai-vs-thespa-gunma-luc-1200-ngay-04-04-2026/",
      "runtime": 1775278800,
      "datetime": "2026-04-04T05:00:00.000Z"
    },
    {
      "name": "Jubilo Iwata vs Ventforet Kofu lúc 12:00",
      "link": "/truc-tiep/jubilo-iwata-vs-ventforet-kofu-luc-1200-ngay-04-04-2026/",
      "runtime": 1775278800,
      "datetime": "2026-04-04T05:00:00.000Z"
    },
    {
      "name": "Shonan Bellmare vs Tochigi SC lúc 12:00",
      "link": "/truc-tiep/shonan-bellmare-vs-tochigi-sc-luc-1200-ngay-04-04-2026/",
      "runtime": 1775278800,
      "datetime": "2026-04-04T05:00:00.000Z"
    },
    {
      "name": "Yokohama FC vs Blaublitz Akita lúc 12:00",
      "link": "/truc-tiep/yokohama-fc-vs-blaublitz-akita-luc-1200-ngay-04-04-2026/",
      "runtime": 1775278800,
      "datetime": "2026-04-04T05:00:00.000Z"
    },
    {
      "name": "Albirex Niigata vs Z. Kanazawa lúc 12:00",
      "link": "/truc-tiep/albirex-niigata-vs-z-kanazawa-luc-1200-ngay-04-04-2026/",
      "runtime": 1775278800,
      "datetime": "2026-04-04T05:00:00.000Z"
    },
    {
      "name": "Yongin FC vs Jeonnam Dragons lúc 12:00 | ZARA",
      "link": "/truc-tiep/yongin-fc-vs-jeonnam-dragons-luc-1200-ngay-04-04-2026/",
      "runtime": 1775278800,
      "datetime": "2026-04-04T05:00:00.000Z"
    },
    {
      "name": "Seoul E-Land FC vs Suwon FC lúc 12:00 | SILVA",
      "link": "/truc-tiep/seoul-e-land-fc-vs-suwon-fc-luc-1200-ngay-04-04-2026/",
      "runtime": 1775278800,
      "datetime": "2026-04-04T05:00:00.000Z"
    },
    {
      "name": "Anyang JungKwanJang vs Ulsan Phoebus lúc 12:00 | ALAN",
      "link": "/truc-tiep/anyang-jungkwanjang-vs-ulsan-phoebus-luc-1200-ngay-04-04-2026/",
      "runtime": 1775278800,
      "datetime": "2026-04-04T05:00:00.000Z"
    },
    {
      "name": "Wonju Dongbu Promy vs Seoul Thunders lúc 12:00",
      "link": "/truc-tiep/wonju-dongbu-promy-vs-seoul-thunders-luc-1200-ngay-04-04-2026/",
      "runtime": 1775278800,
      "datetime": "2026-04-04T05:00:00.000Z"
    },
    {
      "name": "Toray Arrows vs Nagano lúc 12:05",
      "link": "/truc-tiep/toray-arrows-vs-nagano-luc-1205-ngay-04-04-2026/",
      "runtime": 1775279100,
      "datetime": "2026-04-04T05:05:00.000Z"
    },
    {
      "name": "Northern Tigers vs Coast Mariners (R) lúc 12:30",
      "link": "/truc-tiep/northern-tigers-vs-coast-mariners-r-luc-1230-ngay-04-04-2026/",
      "runtime": 1775280600,
      "datetime": "2026-04-04T05:30:00.000Z"
    },
    {
      "name": "Macarthur Rams vs Prospect United SC lúc 12:30",
      "link": "/truc-tiep/macarthur-rams-vs-prospect-united-sc-luc-1230-ngay-04-04-2026/",
      "runtime": 1775280600,
      "datetime": "2026-04-04T05:30:00.000Z"
    },
    {
      "name": "Nagoya Grampus vs Cerezo Osaka lúc 13:00 | FINN",
      "link": "/truc-tiep/nagoya-grampus-vs-cerezo-osaka-luc-1300-ngay-04-04-2026/",
      "runtime": 1775282400,
      "datetime": "2026-04-04T06:00:00.000Z"
    },
    {
      "name": "Central Coast Mariners vs Perth Glory lúc 13:00 | BRADY",
      "link": "/truc-tiep/central-coast-mariners-vs-perth-glory-luc-1300-ngay-04-04-2026/",
      "runtime": 1775282400,
      "datetime": "2026-04-04T06:00:00.000Z"
    },
    {
      "name": "Sydney Olympic vs Sutherland Sharks lúc 13:00",
      "link": "/truc-tiep/sydney-olympic-vs-sutherland-sharks-luc-1300-ngay-04-04-2026/",
      "runtime": 1775282400,
      "datetime": "2026-04-04T06:00:00.000Z"
    },
    {
      "name": "Newcastle Jets (Y) vs Druitt Rangers lúc 13:00",
      "link": "/truc-tiep/newcastle-jets-y-vs-druitt-rangers-luc-1300-ngay-04-04-2026/",
      "runtime": 1775282400,
      "datetime": "2026-04-04T06:00:00.000Z"
    },
    {
      "name": "Blacktown Spartans vs Canterbury Bankstown lúc 13:00",
      "link": "/truc-tiep/blacktown-spartans-vs-canterbury-bankstown-luc-1300-ngay-04-04-2026/",
      "runtime": 1775282400,
      "datetime": "2026-04-04T06:00:00.000Z"
    },
    {
      "name": "Macau University vs Artilheiros lúc 13:00",
      "link": "/truc-tiep/macau-university-vs-artilheiros-luc-1300-ngay-04-04-2026/",
      "runtime": 1775282400,
      "datetime": "2026-04-04T06:00:00.000Z"
    },
    {
      "name": "Daejeon Korail vs Pocheon FC lúc 13:00",
      "link": "/truc-tiep/daejeon-korail-vs-pocheon-fc-luc-1300-ngay-04-04-2026/",
      "runtime": 1775282400,
      "datetime": "2026-04-04T06:00:00.000Z"
    },
    {
      "name": "Osaka Sakai vs Nagoya lúc 13:05",
      "link": "/truc-tiep/osaka-sakai-vs-nagoya-luc-1305-ngay-04-04-2026/",
      "runtime": 1775282700,
      "datetime": "2026-04-04T06:05:00.000Z"
    }
  ]
}