{
  "success": true,
  "total_matches": 66,
  "updated_at": "2026-05-31T08:10:55.828Z",
  "matches": [
    {
      "name": "Darwin Hearts vs Palmerston lúc 13:30",
      "link": "/truc-tiep/darwin-hearts-vs-palmerston-luc-1330-ngay-31-05-2026/",
      "runtime": 1780209000,
      "datetime": "2026-05-31T06:30:00.000Z"
    },
    {
      "name": "Dali Village vs Chejiang 2 Village lúc 13:30",
      "link": "/truc-tiep/dali-village-vs-chejiang-2-village-luc-1330-ngay-31-05-2026/",
      "runtime": 1780209000,
      "datetime": "2026-05-31T06:30:00.000Z"
    },
    {
      "name": "Nữ Apia L Tigers vs Nữ Northern Tigers lúc 13:50",
      "link": "/truc-tiep/nu-apia-l-tigers-vs-nu-northern-tigers-luc-1350-ngay-31-05-2026/",
      "runtime": 1780210200,
      "datetime": "2026-05-31T06:50:00.000Z"
    },
    {
      "name": "St Albans Saints vs Preston Lions lúc 14:00",
      "link": "/truc-tiep/st-albans-saints-vs-preston-lions-luc-1400-ngay-31-05-2026/",
      "runtime": 1780210800,
      "datetime": "2026-05-31T07:00:00.000Z"
    },
    {
      "name": "Mitchelton FC vs SWQ Thunder lúc 14:00",
      "link": "/truc-tiep/mitchelton-fc-vs-swq-thunder-luc-1400-ngay-31-05-2026/",
      "runtime": 1780210800,
      "datetime": "2026-05-31T07:00:00.000Z"
    },
    {
      "name": "Nữ Perth RedStar vs Nữ Football West lúc 14:00",
      "link": "/truc-tiep/nu-perth-redstar-vs-nu-football-west-luc-1400-ngay-31-05-2026/",
      "runtime": 1780210800,
      "datetime": "2026-05-31T07:00:00.000Z"
    },
    {
      "name": "Nữ Sydney Olympic vs Nữ WS Wanderers B lúc 14:40",
      "link": "/truc-tiep/nu-sydney-olympic-vs-nu-ws-wanderers-b-luc-1440-ngay-31-05-2026/",
      "runtime": 1780210800,
      "datetime": "2026-05-31T07:00:00.000Z"
    },
    {
      "name": "Nữ Manly Utd vs Nữ Uni.of Sydney lúc 14:00",
      "link": "/truc-tiep/nu-manly-utd-vs-nu-uni-of-sydney-luc-1400-ngay-31-05-2026/",
      "runtime": 1780210800,
      "datetime": "2026-05-31T07:00:00.000Z"
    },
    {
      "name": "Nữ Moreton City Excelsior vs Nữ The Gap NPL lúc 14:00",
      "link": "/truc-tiep/nu-moreton-city-excelsior-vs-nu-the-gap-npl-luc-1400-ngay-31-05-2026/",
      "runtime": 1780210800,
      "datetime": "2026-05-31T07:00:00.000Z"
    },
    {
      "name": "Nữ UWA-Nedlands FC vs Nữ Balcatta lúc 14:00",
      "link": "/truc-tiep/nu-uwa-nedlands-fc-vs-nu-balcatta-luc-1400-ngay-31-05-2026/",
      "runtime": 1780210800,
      "datetime": "2026-05-31T07:00:00.000Z"
    },
    {
      "name": "Nữ Perth SC vs Nữ Sorrento lúc 14:00",
      "link": "/truc-tiep/nu-perth-sc-vs-nu-sorrento-luc-1400-ngay-31-05-2026/",
      "runtime": 1780210800,
      "datetime": "2026-05-31T07:00:00.000Z"
    },
    {
      "name": "West Adelaide SC vs Adelaide City  lúc 14:15",
      "link": "/truc-tiep/west-adelaide-sc-vs-adelaide-city-luc-1415-ngay-31-05-2026/",
      "runtime": 1780211700,
      "datetime": "2026-05-31T07:15:00.000Z"
    },
    {
      "name": "An Se-young vs Akane Yamaguchi lúc 13:50",
      "link": "/truc-tiep/an-se-young-vs-akane-yamaguchi-luc-1350-ngay-31-05-2026/",
      "runtime": 1780211700,
      "datetime": "2026-05-31T07:15:00.000Z"
    },
    {
      "name": "Hwaseong FC vs Gyeongnam FC lúc 14:30 | MAX",
      "link": "/truc-tiep/hwaseong-fc-vs-gyeongnam-fc-luc-1430-ngay-31-05-2026/",
      "runtime": 1780212600,
      "datetime": "2026-05-31T07:30:00.000Z"
    },
    {
      "name": "Jeonnam Dragons vs Seoul E-Land FC lúc 14:30 | LOUIS",
      "link": "/truc-tiep/jeonnam-dragons-vs-seoul-e-land-fc-luc-1430-ngay-31-05-2026/",
      "runtime": 1780212600,
      "datetime": "2026-05-31T07:30:00.000Z"
    },
    {
      "name": "Nữ Hills United vs Nữ UNSW FC lúc 14:30",
      "link": "/truc-tiep/nu-hills-united-vs-nu-unsw-fc-luc-1430-ngay-31-05-2026/",
      "runtime": 1780212600,
      "datetime": "2026-05-31T07:30:00.000Z"
    },
    {
      "name": "Nữ Subiaco AFC vs Nữ Fremantle City FC  lúc 14:45",
      "link": "/truc-tiep/nu-subiaco-afc-vs-nu-fremantle-city-fc-luc-1445-ngay-31-05-2026/",
      "runtime": 1780213500,
      "datetime": "2026-05-31T07:45:00.000Z"
    },
    {
      "name": "Geumsan Insam FC vs Geoje Citizen lúc 15:00",
      "link": "/truc-tiep/geumsan-insam-fc-vs-geoje-citizen-luc-1500-ngay-31-05-2026/",
      "runtime": 1780214400,
      "datetime": "2026-05-31T08:00:00.000Z"
    },
    {
      "name": "Brisbane Olympic FC vs Brisbane City lúc 15:00 | SILVA",
      "link": "/truc-tiep/brisbane-olympic-fc-vs-brisbane-city-luc-1500-ngay-31-05-2026/",
      "runtime": 1780214400,
      "datetime": "2026-05-31T08:00:00.000Z"
    },
    {
      "name": "Taringa Rovers vs Southside Eagles lúc 15:00",
      "link": "/truc-tiep/taringa-rovers-vs-southside-eagles-luc-1500-ngay-31-05-2026/",
      "runtime": 1780214400,
      "datetime": "2026-05-31T08:00:00.000Z"
    },
    {
      "name": "Wuhai Team vs Bayannur Team lúc 15:00",
      "link": "/truc-tiep/wuhai-team-vs-bayannur-team-luc-1500-ngay-31-05-2026/",
      "runtime": 1780214400,
      "datetime": "2026-05-31T08:00:00.000Z"
    },
    {
      "name": "Yeoju Citizen vs Daejeon Korail lúc 15:00",
      "link": "/truc-tiep/yeoju-citizen-vs-daejeon-korail-luc-1500-ngay-31-05-2026/",
      "runtime": 1780214400,
      "datetime": "2026-05-31T08:00:00.000Z"
    },
    {
      "name": "Nữ Capalaba vs Nữ Queensland Lions lúc 15:00",
      "link": "/truc-tiep/nu-capalaba-vs-nu-queensland-lions-luc-1500-ngay-31-05-2026/",
      "runtime": 1780214400,
      "datetime": "2026-05-31T08:00:00.000Z"
    },
    {
      "name": "Nữ Ukraine U16 vs Nữ Slovakia U16 lúc 15:00",
      "link": "/truc-tiep/nu-ukraine-u16-vs-nu-slovakia-u16-luc-1500-ngay-31-05-2026/",
      "runtime": 1780214400,
      "datetime": "2026-05-31T08:00:00.000Z"
    },
    {
      "name": "Nữ Montenegro U16 vs Nữ Turkey U16 lúc 15:00",
      "link": "/truc-tiep/nu-montenegro-u16-vs-nu-turkey-u16-luc-1500-ngay-31-05-2026/",
      "runtime": 1780214400,
      "datetime": "2026-05-31T08:00:00.000Z"
    },
    {
      "name": "Benjamin Winter Lopez vs Nicolas Alvarez Varona lúc 15:00",
      "link": "/truc-tiep/benjamin-winter-lopez-vs-nicolas-alvarez-varona-luc-1500-ngay-31-05-2026/",
      "runtime": 1780214400,
      "datetime": "2026-05-31T08:00:00.000Z"
    },
    {
      "name": "Fredit BRION vs Hanwha Life Esports lúc 15:00 | MARTY",
      "link": "/truc-tiep/fredit-brion-vs-hanwha-life-esports-luc-1500-ngay-31-05-2026/",
      "runtime": 1780214400,
      "datetime": "2026-05-31T08:00:00.000Z"
    },
    {
      "name": "Atreides vs G2 Ares lúc 15:00",
      "link": "/truc-tiep/atreides-vs-g2-ares-luc-1500-ngay-31-05-2026/",
      "runtime": 1780214400,
      "datetime": "2026-05-31T08:00:00.000Z"
    },
    {
      "name": "Brno B vs Hlucin lúc 15:15",
      "link": "/truc-tiep/brno-b-vs-hlucin-luc-1515-ngay-31-05-2026/",
      "runtime": 1780215300,
      "datetime": "2026-05-31T08:15:00.000Z"
    },
    {
      "name": "Sigma Olomouc B vs Blansko lúc 15:15",
      "link": "/truc-tiep/sigma-olomouc-b-vs-blansko-luc-1515-ngay-31-05-2026/",
      "runtime": 1780215300,
      "datetime": "2026-05-31T08:15:00.000Z"
    },
    {
      "name": "Mathias Christiansen/Alexandra Boje vs Yuichi Shimogami/Sayaka Hobara lúc 14:40",
      "link": "/truc-tiep/mathias-christiansen-alexandra-boje-vs-yuichi-shimogami-sayaka-hobara-luc-1440-ngay-31-05-2026/",
      "runtime": 1780215600,
      "datetime": "2026-05-31T08:20:00.000Z"
    },
    {
      "name": "Zhuhai Team vs Guangzhou Team lúc 15:30",
      "link": "/truc-tiep/zhuhai-team-vs-guangzhou-team-luc-1530-ngay-31-05-2026/",
      "runtime": 1780216200,
      "datetime": "2026-05-31T08:30:00.000Z"
    },
    {
      "name": "Anle Village vs Dangxiang Village lúc 15:30",
      "link": "/truc-tiep/anle-village-vs-dangxiang-village-luc-1530-ngay-31-05-2026/",
      "runtime": 1780216200,
      "datetime": "2026-05-31T08:30:00.000Z"
    },
    {
      "name": "TPF Uttaradit vs Muang Loei United lúc 15:30",
      "link": "/truc-tiep/tpf-uttaradit-vs-muang-loei-united-luc-1530-ngay-31-05-2026/",
      "runtime": 1780216200,
      "datetime": "2026-05-31T08:30:00.000Z"
    },
    {
      "name": "Haman FC vs Jinju Citizen lúc 12:00",
      "link": "/truc-tiep/haman-fc-vs-jinju-citizen-luc-1200-ngay-31-05-2026/",
      "runtime": 1780218000,
      "datetime": "2026-05-31T09:00:00.000Z"
    },
    {
      "name": "Moggill FC vs Yeronga Eagles lúc 16:00",
      "link": "/truc-tiep/moggill-fc-vs-yeronga-eagles-luc-1600-ngay-31-05-2026/",
      "runtime": 1780218000,
      "datetime": "2026-05-31T09:00:00.000Z"
    },
    {
      "name": "Grulla Morioka vs J-Lease FC lúc 16:00",
      "link": "/truc-tiep/grulla-morioka-vs-j-lease-fc-luc-1600-ngay-31-05-2026/",
      "runtime": 1780218000,
      "datetime": "2026-05-31T09:00:00.000Z"
    },
    {
      "name": "Yadanarbon  U20 vs Thitsar Arman FC lúc 16:00",
      "link": "/truc-tiep/yadanarbon-u20-vs-thitsar-arman-fc-luc-1600-ngay-31-05-2026/",
      "runtime": 1780218000,
      "datetime": "2026-05-31T09:00:00.000Z"
    },
    {
      "name": "Mahar United U20 vs ISPE FC U20 lúc 16:00",
      "link": "/truc-tiep/mahar-united-u20-vs-ispe-fc-u20-luc-1600-ngay-31-05-2026/",
      "runtime": 1780218000,
      "datetime": "2026-05-31T09:00:00.000Z"
    },
    {
      "name": "New Taipei Kings vs Formosa Dreamers lúc 16:00 | ALAN",
      "link": "/truc-tiep/new-taipei-kings-vs-formosa-dreamers-luc-1600-ngay-31-05-2026/",
      "runtime": 1780218000,
      "datetime": "2026-05-31T09:00:00.000Z"
    },
    {
      "name": "Marta Kostyuk vs Iga Swiatek lúc 16:00 | VIC",
      "link": "/truc-tiep/marta-kostyuk-vs-iga-swiatek-luc-1600-ngay-31-05-2026/",
      "runtime": 1780218000,
      "datetime": "2026-05-31T09:00:00.000Z"
    },
    {
      "name": "Sorana Cirstea vs Wang Xiyu lúc 16:00 | LUCAS",
      "link": "/truc-tiep/sorana-cirstea-vs-wang-xiyu-luc-1600-ngay-31-05-2026/",
      "runtime": 1780218000,
      "datetime": "2026-05-31T09:00:00.000Z"
    },
    {
      "name": "Jacopo Vasami vs Lukas Neumayer lúc 16:00",
      "link": "/truc-tiep/jacopo-vasami-vs-lukas-neumayer-luc-1600-ngay-31-05-2026/",
      "runtime": 1780218000,
      "datetime": "2026-05-31T09:00:00.000Z"
    },
    {
      "name": "Team Secret Whales vs Deep Cross Gaming lúc 16:00",
      "link": "/truc-tiep/team-secret-whales-vs-deep-cross-gaming-luc-1600-ngay-31-05-2026/",
      "runtime": 1780218000,
      "datetime": "2026-05-31T09:00:00.000Z"
    },
    {
      "name": "JD Gaming vs Top Esports lúc 16:00",
      "link": "/truc-tiep/jd-gaming-vs-top-esports-luc-1600-ngay-31-05-2026/",
      "runtime": 1780218000,
      "datetime": "2026-05-31T09:00:00.000Z"
    },
    {
      "name": "Satwiksairaj Rankireddy/Chirag Shetty vs Fajar Alfian/Muhammad Shohibul Fikri lúc 15:30",
      "link": "/truc-tiep/satwiksairaj-rankireddy-chirag-shetty-vs-fajar-alfian-muhammad-shohibul-fikri-luc-1530-ngay-31-05-2026/",
      "runtime": 1780218600,
      "datetime": "2026-05-31T09:10:00.000Z"
    },
    {
      "name": "Shine Elastopainters vs Barangay Ginebra lúc 16:15 | STEP",
      "link": "/truc-tiep/shine-elastopainters-vs-barangay-ginebra-luc-1615-ngay-31-05-2026/",
      "runtime": 1780218900,
      "datetime": "2026-05-31T09:15:00.000Z"
    },
    {
      "name": "Ansan Greeners vs Cheonan City lúc 17:00 | FINN",
      "link": "/truc-tiep/ansan-greeners-vs-cheonan-city-luc-1700-ngay-31-05-2026/",
      "runtime": 1780221600,
      "datetime": "2026-05-31T10:00:00.000Z"
    },
    {
      "name": "Nữ Real Madrid vs Nữ Granada lúc 17:00 | HELLO",
      "link": "/truc-tiep/nu-real-madrid-vs-nu-granada-luc-1700-ngay-31-05-2026/",
      "runtime": 1780221600,
      "datetime": "2026-05-31T10:00:00.000Z"
    },
    {
      "name": "Nữ Real Sociedad vs Nữ Atletico Madrid lúc 17:00 | KEN",
      "link": "/truc-tiep/nu-real-sociedad-vs-nu-atletico-madrid-luc-1700-ngay-31-05-2026/",
      "runtime": 1780221600,
      "datetime": "2026-05-31T10:00:00.000Z"
    },
    {
      "name": "Nữ Eibar vs Nữ Logrono  lúc 17:00",
      "link": "/truc-tiep/nu-eibar-vs-nu-logrono-luc-1700-ngay-31-05-2026/",
      "runtime": 1780221600,
      "datetime": "2026-05-31T10:00:00.000Z"
    },
    {
      "name": "Nữ Sejong Sportstoto  vs Nữ Seoul Amazones lúc 17:00",
      "link": "/truc-tiep/nu-sejong-sportstoto-vs-nu-seoul-amazones-luc-1700-ngay-31-05-2026/",
      "runtime": 1780221600,
      "datetime": "2026-05-31T10:00:00.000Z"
    },
    {
      "name": "FK Kosmos vs Chertanovo Moscow lúc 17:00",
      "link": "/truc-tiep/fk-kosmos-vs-chertanovo-moscow-luc-1700-ngay-31-05-2026/",
      "runtime": 1780221600,
      "datetime": "2026-05-31T10:00:00.000Z"
    },
    {
      "name": "Gorilla Universe vs Shao Jiang lúc 17:00",
      "link": "/truc-tiep/gorilla-universe-vs-shao-jiang-luc-1700-ngay-31-05-2026/",
      "runtime": 1780221600,
      "datetime": "2026-05-31T10:00:00.000Z"
    },
    {
      "name": "FC Gomel B vs Slutsk FC lúc 17:00",
      "link": "/truc-tiep/fc-gomel-b-vs-slutsk-fc-luc-1700-ngay-31-05-2026/",
      "runtime": 1780221600,
      "datetime": "2026-05-31T10:00:00.000Z"
    },
    {
      "name": "Taiwan Power vs Ming Chuan Desafio lúc 17:00",
      "link": "/truc-tiep/taiwan-power-vs-ming-chuan-desafio-luc-1700-ngay-31-05-2026/",
      "runtime": 1780221600,
      "datetime": "2026-05-31T10:00:00.000Z"
    },
    {
      "name": "Krylia Sovetov-2 vs Stroitel Kamensk lúc 17:00",
      "link": "/truc-tiep/krylia-sovetov-2-vs-stroitel-kamensk-luc-1700-ngay-31-05-2026/",
      "runtime": 1780221600,
      "datetime": "2026-05-31T10:00:00.000Z"
    },
    {
      "name": "Gil Vicente FC Women vs Nữ Rio Ave lúc 17:00",
      "link": "/truc-tiep/gil-vicente-fc-women-vs-nu-rio-ave-luc-1700-ngay-31-05-2026/",
      "runtime": 1780221600,
      "datetime": "2026-05-31T10:00:00.000Z"
    },
    {
      "name": "Alex Lanier vs Loh Kean Yew lúc 16:20",
      "link": "/truc-tiep/alex-lanier-vs-loh-kean-yew-luc-1620-ngay-31-05-2026/",
      "runtime": 1780221600,
      "datetime": "2026-05-31T10:00:00.000Z"
    },
    {
      "name": "Meavedron vs eSuba lúc 21:00",
      "link": "/truc-tiep/meavedron-vs-esuba-luc-2100-ngay-31-05-2026/",
      "runtime": 1780221600,
      "datetime": "2026-05-31T10:00:00.000Z"
    },
    {
      "name": "Lille Esport vs Project Conquerors lúc 17:00",
      "link": "/truc-tiep/lille-esport-vs-project-conquerors-luc-1700-ngay-31-05-2026/",
      "runtime": 1780221600,
      "datetime": "2026-05-31T10:00:00.000Z"
    },
    {
      "name": "Nongshim RedForce vs Dplus lúc 17:00 | MARTY",
      "link": "/truc-tiep/nongshim-redforce-vs-dplus-luc-1700-ngay-31-05-2026/",
      "runtime": 1780221600,
      "datetime": "2026-05-31T10:00:00.000Z"
    },
    {
      "name": "TDK vs OG lúc 17:00",
      "link": "/truc-tiep/tdk-vs-og-luc-1700-ngay-31-05-2026/",
      "runtime": 1780221600,
      "datetime": "2026-05-31T10:00:00.000Z"
    },
    {
      "name": "LGD Gaming vs Balu Team lúc 17:00",
      "link": "/truc-tiep/lgd-gaming-vs-balu-team-luc-1700-ngay-31-05-2026/",
      "runtime": 1780221600,
      "datetime": "2026-05-31T10:00:00.000Z"
    },
    {
      "name": "Elina Svitolina vs Belinda Bencic lúc 17:10 | VIC",
      "link": "/truc-tiep/elina-svitolina-vs-belinda-bencic-luc-1710-ngay-31-05-2026/",
      "runtime": 1780222200,
      "datetime": "2026-05-31T10:10:00.000Z"
    },
    {
      "name": "Rafael Jodar vs Pablo Carreño Busta lúc 17:10",
      "link": "/truc-tiep/rafael-jodar-vs-pablo-carreno-busta-luc-1710-ngay-31-05-2026/",
      "runtime": 1780222200,
      "datetime": "2026-05-31T10:10:00.000Z"
    }
  ]
}